sea5kg_cpplint/__init__.py
sea5kg_cpplint/__main__.py
sea5kg_cpplint/sea5kg_cpplint.py
sea5kg_cpplint/sea5kg_cpplint_config.py
sea5kg_cpplint-0.0.1.dist-info/LICENSE
sea5kg_cpplint-0.0.1.dist-info/METADATA
sea5kg_cpplint-0.0.1.dist-info/WHEEL
sea5kg_cpplint-0.0.1.dist-info/top_level.txt
sea5kg_cpplint-0.0.1.dist-info/RECORD
