Metadata-Version: 2.1
Name: sea5kg-cpplint
Version: 0.0.1
Summary: FreeHackQuest Python Client Library for fhq-server
Home-page: https://github.com/sea-kg/sea5kg_cpplint
Author: Evgenii Sopov
Author-email: mrseakg@gmail.com
License: UNKNOWN
Keywords: cpplint
Platform: UNKNOWN
Classifier: Programming Language :: Python :: 3
Classifier: License :: OSI Approved :: Apache Software License
Classifier: Operating System :: OS Independent
Requires-Python: >=3.6
